LICENCE-BRUKER.txt
LICENCE-BSD2.txt
LICENCE.txt
MANIFEST.in
README.md
THIRD-PARTY-LICENSE-README.txt
original_bruker_tdf_readme.txt
redist.txt
setup.cfg
setup.py
opentims_bruker_bridge/__init__.py
opentims_bruker_bridge/libtimsdata.so
opentims_bruker_bridge.egg-info/PKG-INFO
opentims_bruker_bridge.egg-info/SOURCES.txt
opentims_bruker_bridge.egg-info/dependency_links.txt
opentims_bruker_bridge.egg-info/not-zip-safe
opentims_bruker_bridge.egg-info/top_level.txt
opentims_bruker_bridge/win32/timsdata.dll
opentims_bruker_bridge/win64/timsdata.dll