Metadata-Version: 1.1
Name: opentims-bruker-bridge
Version: 1.0.3
Summary: Bruker dll and so files.
Home-page: https://github.com/MatteoLacki/opentims_bruker_bridge.git
Author: MatteoLacki
Author-email: matteo.lacki@gmail.com
License: UNKNOWN
Keywords: OpenTIMS,TimsTOF
Platform: UNKNOWN
Classifier: Development Status :: 4 - Beta
Classifier: Intended Audience :: Science/Research
Classifier: Topic :: Scientific/Engineering :: Chemistry
Classifier: Programming Language :: Python :: 3.6
Classifier: Programming Language :: Python :: 3.7
Classifier: Programming Language :: Python :: 3.8
Classifier: Programming Language :: Python :: 3.9
